Netaxgenere/__init__.py
Netaxgenere/network.cpython-311-darwin.so
Netaxgenere-0.1.1.dist-info/LICENSE.txt
Netaxgenere-0.1.1.dist-info/METADATA
Netaxgenere-0.1.1.dist-info/WHEEL
Netaxgenere-0.1.1.dist-info/top_level.txt
Netaxgenere-0.1.1.dist-info/RECORD
