Metadata-Version: 2.1
Name: Netaxgenere
Version: 0.1.1
Summary: A package for prepare network files
Author: YY
Classifier: Programming Language :: Python :: 3
Classifier: Programming Language :: Python :: 3.7
Classifier: Programming Language :: Python :: 3.8
Classifier: Programming Language :: Python :: 3.9
License-File: LICENSE.txt
